{
	"type": "minecraft:entity",
    "pools":
	[
        {
            "rolls": 1,
            "entries":
			[
                {
                    "type": "minecraft:item",
                    "name": "minecraft:cobblestone",
                    "conditions":
					[
                        {
                            "condition": "minecraft:random_chance_with_looting",
                            "chance": 0.05,
							"looting_multiplier": 0.005
                        }
                    ],
                    "functions":
					[
                        {
                            "function": "minecraft:set_count",
                            "count":
							{
                                "min": 0.0,
                                "max": 2.0,
								"type": "minecraft:uniform"
                            },
							"conditions":
							[
								{
									"condition": "minecraft:entity_scores",
									"entity": "killer",
									"scores":
									{
										"double_loot": 0
									}
								}
							]
                        },
						{
                            "function": "minecraft:set_count",
                            "count":
							{
                                "min": 1.0,
                                "max": 4.0,
								"type": "minecraft:uniform"
                            },
							"conditions":
							[
								{
									"condition": "minecraft:entity_scores",
									"entity": "killer",
									"scores":
									{
										"double_loot": 1
									}
								}
							]
                        }
                    ]
                }
            ]
        }
    ]
}